sibr_module/__init__.py
sibr_module/bigquery.py
sibr_module/logging.py
sibr_module/secrets.py
sibr_module/storage.py
sibr_module-0.2.11.dist-info/LICENSE
sibr_module-0.2.11.dist-info/METADATA
sibr_module-0.2.11.dist-info/WHEEL
sibr_module-0.2.11.dist-info/RECORD
