Metadata-Version: 2.3
Name: sibr-module
Version: 0.2.11
Summary: A collection of helper modules for interacting with Google Cloud Platform services, designed to simplify common workflows.
License: MIT
Author: sigvardbratlie
Author-email: sigvard.bratlie@gmail.com
Requires-Python: >=3.11
Classifier: License :: OSI Approved :: MIT License
Classifier: Programming Language :: Python :: 3
Classifier: Programming Language :: Python :: 3.11
Classifier: Programming Language :: Python :: 3.12
Classifier: Programming Language :: Python :: 3.13
Provides-Extra: all
Provides-Extra: bigquery
Provides-Extra: logging
Provides-Extra: secrets
Provides-Extra: storage
Requires-Dist: bigframes (>=2.17,<3.0) ; extra == "bigquery"
Requires-Dist: db-dtypes (>=1.4,<2.0) ; extra == "bigquery"
Requires-Dist: gcsfs (>=2025.7,<2026.0) ; extra == "storage"
Requires-Dist: google-api-core (>=2.25,<3.0)
Requires-Dist: google-auth (>=2.40,<3.0)
Requires-Dist: google-cloud-bigquery (>=3.36,<4.0) ; extra == "bigquery"
Requires-Dist: google-cloud-logging (>=3.12,<4.0) ; extra == "logging"
Requires-Dist: google-cloud-secret-manager (>=2.24,<3.0) ; extra == "secrets"
Requires-Dist: google-cloud-storage (>=2.10,<4.0) ; extra == "storage"
Requires-Dist: joblib (>=1.0.0,<2.0) ; extra == "bigquery"
Requires-Dist: pandas (>=2.3,<3.0)
Requires-Dist: pandas-gbq (>=0.29,<0.30) ; extra == "bigquery"
Requires-Dist: pyarrow (>=21.0,<22.0) ; extra == "bigquery"
Requires-Dist: python-dotenv (>=1.0,<2.0)
Requires-Dist: pyyaml (>=6.0,<7.0) ; extra == "bigquery"
Requires-Dist: sibr-module[bigquery] ; extra == "all"
Requires-Dist: sibr-module[logging] ; extra == "all"
Requires-Dist: sibr-module[secrets] ; extra == "all"
Requires-Dist: sibr-module[storage] ; extra == "all"
